<annotations><folder>JPEGImages</folder><filename>C1_P12_N1_S4_1.JPG</filename><path>../</path><source><database>Unknown</database></source><size><width>1761</width><height>2448</height><depth>1</depth></size><segmented>0</segmented><object><name>Product</name><pose>Unspecified</pose><truncated>0</truncated><difficult>0</difficult><bndbox><xmin>100</xmin><ymin>768</ymin><xmax>316</xmax><ymax>1080</ymax></bndbox></object><object><name>Product</name><pose>Unspecified</pose><truncated>0</truncated><difficult>0</difficult><bndbox><xmin>108</xmin><ymin>200</ymin><xmax>324</xmax><ymax>496</ymax></bndbox></object><object><name>Product</name><pose>Unspecified</pose><truncated>0</truncated><difficult>0</difficult><bndbox><xmin>1172</xmin><ymin>1364</ymin><xmax>1408</xmax><ymax>1712</ymax></bndbox></object><object><name>Product</name><pose>Unspecified</pose><truncated>0</truncated><difficult>0</difficult><bndbox><xmin>1180</xmin><ymin>776</ymin><xmax>1396</xmax><ymax>1088</ymax></bndbox></object><object><name>Product</name><pose>Unspecified</pose><truncated>0</truncated><difficult>0</difficult><bndbox><xmin>1184</xmin><ymin>164</ymin><xmax>1400</xmax><ymax>460</ymax></bndbox></object><object><name>Product</name><pose>Unspecified</pose><truncated>0</truncated><difficult>0</difficult><bndbox><xmin>1188</xmin><ymin>1976</ymin><xmax>1404</xmax><ymax>2324</ymax></bndbox></object><object><name>Product</name><pose>Unspecified</pose><truncated>0</truncated><difficult>0</difficult><bndbox><xmin>1392</xmin><ymin>1368</ymin><xmax>1628</xmax><ymax>1716</ymax></bndbox></object><object><name>Product</name><pose>Unspecified</pose><truncated>0</truncated><difficult>0</difficult><bndbox><xmin>1420</xmin><ymin>716</ymin><xmax>1636</xmax><ymax>1096</ymax></bndbox></object><object><name>Product</name><pose>Unspecified</pose><truncated>0</truncated><difficult>0</difficult><bndbox><xmin>1424</xmin><ymin>160</ymin><xmax>1640</xmax><ymax>456</ymax></bndbox></object><object><name>Product</name><pose>Unspecified</pose><truncated>0</truncated><difficult>0</difficult><bndbox><xmin>308</xmin><ymin>772</ymin><xmax>524</xmax><ymax>1084</ymax></bndbox></object><object><name>Product</name><pose>Unspecified</pose><truncated>0</truncated><difficult>0</difficult><bndbox><xmin>316</xmin><ymin>200</ymin><xmax>532</xmax><ymax>496</ymax></bndbox></object><object><name>Product</name><pose>Unspecified</pose><truncated>0</truncated><difficult>0</difficult><bndbox><xmin>500</xmin><ymin>1972</ymin><xmax>716</xmax><ymax>2320</ymax></bndbox></object><object><name>Product</name><pose>Unspecified</pose><truncated>0</truncated><difficult>0</difficult><bndbox><xmin>520</xmin><ymin>776</ymin><xmax>736</xmax><ymax>1088</ymax></bndbox></object><object><name>Product</name><pose>Unspecified</pose><truncated>0</truncated><difficult>0</difficult><bndbox><xmin>532</xmin><ymin>1352</ymin><xmax>740</xmax><ymax>1700</ymax></bndbox></object><object><name>Product</name><pose>Unspecified</pose><truncated>0</truncated><difficult>0</difficult><bndbox><xmin>548</xmin><ymin>196</ymin><xmax>764</xmax><ymax>492</ymax></bndbox></object><object><name>Product</name><pose>Unspecified</pose><truncated>0</truncated><difficult>0</difficult><bndbox><xmin>728</xmin><ymin>1972</ymin><xmax>944</xmax><ymax>2320</ymax></bndbox></object><object><name>Product</name><pose>Unspecified</pose><truncated>0</truncated><difficult>0</difficult><bndbox><xmin>732</xmin><ymin>1352</ymin><xmax>952</xmax><ymax>1700</ymax></bndbox></object><object><name>Product</name><pose>Unspecified</pose><truncated>0</truncated><difficult>0</difficult><bndbox><xmin>736</xmin><ymin>776</ymin><xmax>952</xmax><ymax>1088</ymax></bndbox></object><object><name>Product</name><pose>Unspecified</pose><truncated>0</truncated><difficult>0</difficult><bndbox><xmin>740</xmin><ymin>184</ymin><xmax>956</xmax><ymax>480</ymax></bndbox></object><object><name>Product</name><pose>Unspecified</pose><truncated>0</truncated><difficult>0</difficult><bndbox><xmin>88</xmin><ymin>1316</ymin><xmax>304</xmax><ymax>1696</ymax></bndbox></object><object><name>Product</name><pose>Unspecified</pose><truncated>0</truncated><difficult>0</difficult><bndbox><xmin>944</xmin><ymin>1376</ymin><xmax>1164</xmax><ymax>1724</ymax></bndbox></object><object><name>Product</name><pose>Unspecified</pose><truncated>0</truncated><difficult>0</difficult><bndbox><xmin>944</xmin><ymin>776</ymin><xmax>1160</xmax><ymax>1088</ymax></bndbox></object><object><name>Product</name><pose>Unspecified</pose><truncated>0</truncated><difficult>0</difficult><bndbox><xmin>948</xmin><ymin>180</ymin><xmax>1164</xmax><ymax>476</ymax></bndbox></object><object><name>Product</name><pose>Unspecified</pose><truncated>0</truncated><difficult>0</difficult><bndbox><xmin>960</xmin><ymin>1980</ymin><xmax>1176</xmax><ymax>2328</ymax></bndbox></object><object><name>Product</name><pose>Unspecified</pose><truncated>0</truncated><difficult>0</difficult><bndbox><xmin>1400</xmin><ymin>1956</ymin><xmax>1604</xmax><ymax>2336</ymax></bndbox></object><object><name>Product</name><pose>Unspecified</pose><truncated>0</truncated><difficult>0</difficult><bndbox><xmin>292</xmin><ymin>1972</ymin><xmax>508</xmax><ymax>2320</ymax></bndbox></object><object><name>Product</name><pose>Unspecified</pose><truncated>0</truncated><difficult>0</difficult><bndbox><xmin>92</xmin><ymin>1976</ymin><xmax>308</xmax><ymax>2324</ymax></bndbox></object></annotations>